{"title":"我的博客之旅：学习、分享与成长","uid":"fca5d0f1b5b938fde80803f8dc301aa3","slug":"我的第一篇博客","date":"2023-07-14T09:16:53.000Z","updated":"2023-07-15T09:15:33.203Z","comments":true,"path":"api/articles/我的第一篇博客.json","keywords":null,"cover":"https://cdn.jsdelivr.net/gh/GeneralK1ng/My_Blog_IMG@main/img/XJTLU_CB.JPG","content":"<blockquote><span class=\"custom-blockquote-svg\"><svg width=\"24\" height=\"24\" viewBox=\"0 0 24 24\" fill=\"\" xmlns=\"http://www.w3.org/2000/svg\" data-reactroot=\"\">\n<path fill=\"\" d=\"M22 12C22 6.5 17.5 2 12 2C6.5 2 2 6.5 2 12C2 17.5 6.5 22 12 22C13.8 22 15.5 21.5 17 20.6L22 22L20.7 17C21.5 15.5 22 13.8 22 12Z\" undefined=\"1\"></path>\n<path fill=\"\" d=\"M15.97 11.5H16.04C17.12 11.5 18 12.38 18 13.47V13.53C18 14.62 17.12 15.5 16.03 15.5H15.96C14.88 15.5 14 14.62 14 13.53V13.46C14 12.38 14.88 11.5 15.97 11.5Z\" undefined=\"1\"></path>\n<path fill=\"\" d=\"M7.97 11.5H8.04C9.12 11.5 10 12.38 10 13.47V13.53C10 14.62 9.12 15.5 8.03 15.5H7.97C6.88 15.5 6 14.62 6 13.53V13.46C6 12.38 6.88 11.5 7.97 11.5Z\" undefined=\"1\"></path>\n<path stroke-linejoin=\"round\" stroke-linecap=\"round\" stroke-miterlimit=\"10\" stroke-width=\"2\" stroke=\"\" d=\"M17 8.5C15.23 8.97 14.07 10.84 14.01 13.27C14 13.33 14 13.4 14 13.47V13.5\"></path>\n<path stroke-linejoin=\"round\" stroke-linecap=\"round\" stroke-miterlimit=\"10\" stroke-width=\"2\" stroke=\"\" d=\"M9 8.5C7.23 8.97 6.07 10.84 6.01 13.27C6 13.33 6 13.4 6 13.47V13.5\"></path>\n<path stroke-linejoin=\"round\" stroke-linecap=\"round\" stroke-miterlimit=\"10\" stroke-width=\"2\" stroke=\"\" d=\"M15.97 11.5H16.04C17.12 11.5 18 12.38 18 13.47V13.53C18 14.62 17.12 15.5 16.03 15.5H15.96C14.88 15.5 14 14.62 14 13.53V13.46C14 12.38 14.88 11.5 15.97 11.5Z\"></path>\n<path stroke-linejoin=\"round\" stroke-linecap=\"round\" stroke-miterlimit=\"10\" stroke-width=\"2\" stroke=\"\" d=\"M7.97 11.5H8.04C9.12 11.5 10 12.38 10 13.47V13.53C10 14.62 9.12 15.5 8.03 15.5H7.97C6.88 15.5 6 14.62 6 13.53V13.46C6 12.38 6.88 11.5 7.97 11.5Z\"></path>\n</svg>\n</span><p>欢迎来到我的博客！我是金洪来，目前就读于西交利物浦大学，专业是信息与计算科学（ICS）。在我充满好奇心和激情的探索中，我决定搭建这个博客，与大家分享我的学习经历、见解和成果。对我来说，这是一次意义非凡的旅程，我希望能够与你们一起成长、互相学习和建立联系。</p></blockquote>\n<h2 id=\"自我介绍\"><a href=\"#自我介绍\" class=\"headerlink\" title=\"自我介绍\"></a>自我介绍</h2><p>我是一个对新兴技术充满热情的学生，同时也热爱广泛阅读。在我信息与计算科学的学习中，我不仅学习了编程语言和算法，还探索了许多有趣的领域，如人工智能、数据科学和网络安全。我迷恋于技术的力量和它所带来的无限可能。通过博客，我希望能够与大家分享我的学习经验、项目经历以及对技术和生活的思考。</p>\n<h2 id=\"搭建博客的动机\"><a href=\"#搭建博客的动机\" class=\"headerlink\" title=\"搭建博客的动机\"></a>搭建博客的动机</h2><p>我为什么突然决定搭建博客呢？首先，学习新技术时，我发现将所学知识记录下来是一种非常有效的方法，可以帮助我更好地理解和巩固所学内容。通过博客，我可以分享这些知识，并与志同道合的人们交流和互动，从中收获更多的见解和观点。其次，博客可以成为一个平台，让我与专业人士和技术大佬们建立联系。我希望能够从他们的经验中获得启发和指导，进一步提升自己的技术能力和职业发展。最重要的是，我相信博客是一个分享和学习的场所，我希望能够通过博客与读者们一起成长，共同进步。</p>\n<h2 id=\"目标受众\"><a href=\"#目标受众\" class=\"headerlink\" title=\"目标受众\"></a>目标受众</h2><p>我的博客欢迎所有学生、志同道合的朋友、技术大佬和技术小白们。无论你是正在学习编程的初学者，还是想深入了解某个领域的专业人士，我都希望我的博客能够为你提供有价值的信息和灵感。在我的博客中，你将找到关于技术教程、项目经验、学习心得，以及我对生活和工作的见解和体验分享。我希望能够为你提供有趣且实用的内容，无论你身在何处、经历如何，我都希望我的博客能够成为你学习和成长的伙伴。</p>\n<h2 id=\"博客内容计划\"><a href=\"#博客内容计划\" class=\"headerlink\" title=\"博客内容计划\"></a>博客内容计划</h2><p>在我的博客中，你将看到各种内容，涵盖了技术教程、项目经验、学习笔记以及我对生活和工作的见解和体验。我计划分享一些简单易懂的技术教程，帮助初学者快速入门。通过清晰的代码示例和详细的解释，我希望能够让你轻松理解复杂的概念和技术。同时，我也会分享一些我在项目中遇到的挑战和解决方法，以及学习过程中的心得体会。我相信通过分享这些经验，我们可以相互帮助和共同成长。此外，我会不定期地分享一些生活感悟和工作经验，希望能够给你带来一些启发和思考。</p>\n<h2 id=\"学习和成长\"><a href=\"#学习和成长\" class=\"headerlink\" title=\"学习和成长\"></a>学习和成长</h2><p>通过搭建博客，我期望自己能够不断学习和成长。通过与读者的互动和交流，我相信我可以提升自己的学习能力和沟通技巧。我希望能够给你提供有价值的内容和支持，帮助你解决问题、开拓思路。同时，我也希望能够通过博客启发更多的人，鼓励他们追求自己的梦想，勇敢地探索未知的领域。在这个博客的旅程中，我将不断挑战自我，拓宽自己的知识边界，并将这些经验和成长与大家分享。</p>\n<h2 id=\"结语\"><a href=\"#结语\" class=\"headerlink\" title=\"结语\"></a>结语</h2><p>感谢你花时间阅读我的博客介绍。我希望你能够加入我的博客之旅，与我一起探索技术的奇妙世界，共同成长和学习。如果你对我的博客感兴趣或有任何问题、建议或想法，请随时与我联系。我期待与你在博客中互动，并希望我的博客能够对你有所帮助。谢谢！</p>\n","text":" 欢迎来到我的博客！我是金洪来，目前就读于西交利物浦大学，专业是信息与计算科学（ICS）。在我充满好奇心和激情的探索中，我决定搭建这个博客，与大家分享我的学习经历、见解和成果。对我来说，这是一次意义非凡的旅程，我希望能够与你们一起成长、互相学习和建立联系。 自我介绍我是一个对新兴...","link":"","photos":[],"count_time":{"symbolsCount":"1.2k","symbolsTime":"1 mins."},"categories":[],"tags":[{"name":"随笔","slug":"随笔","count":1,"path":"api/tags/随笔.json"}],"toc":"<ol class=\"toc\"><li class=\"toc-item toc-level-2\"><a class=\"toc-link\" href=\"#%E8%87%AA%E6%88%91%E4%BB%8B%E7%BB%8D\"><span class=\"toc-text\">自我介绍</span></a></li><li class=\"toc-item toc-level-2\"><a class=\"toc-link\" href=\"#%E6%90%AD%E5%BB%BA%E5%8D%9A%E5%AE%A2%E7%9A%84%E5%8A%A8%E6%9C%BA\"><span class=\"toc-text\">搭建博客的动机</span></a></li><li class=\"toc-item toc-level-2\"><a class=\"toc-link\" href=\"#%E7%9B%AE%E6%A0%87%E5%8F%97%E4%BC%97\"><span class=\"toc-text\">目标受众</span></a></li><li class=\"toc-item toc-level-2\"><a class=\"toc-link\" href=\"#%E5%8D%9A%E5%AE%A2%E5%86%85%E5%AE%B9%E8%AE%A1%E5%88%92\"><span class=\"toc-text\">博客内容计划</span></a></li><li class=\"toc-item toc-level-2\"><a class=\"toc-link\" href=\"#%E5%AD%A6%E4%B9%A0%E5%92%8C%E6%88%90%E9%95%BF\"><span class=\"toc-text\">学习和成长</span></a></li><li class=\"toc-item toc-level-2\"><a class=\"toc-link\" href=\"#%E7%BB%93%E8%AF%AD\"><span class=\"toc-text\">结语</span></a></li></ol>","author":{"name":"General_K1ng","slug":"blog-author","avatar":"https://cdn.jsdelivr.net/gh/GeneralK1ng/My_Blog_IMG@main/img/avatar.png","link":"/","description":"一名正在努力学习计算机的菜鸟","socials":{"github":"","twitter":"","stackoverflow":"","wechat":"","qq":"","weibo":"","zhihu":"","csdn":"","juejin":"","customs":{"bilibili":{"icon":"/svg/BILIBILI.svg","link":"https://space.bilibili.com/32927332"},"csdn":{"icon":"/svg/csdn.svg","link":"https://blog.csdn.net/qq_34849354"},"github":{"icon":"/svg/GitHub.svg","link":"https://github.com/GeneralK1ng"},"QQ":{"icon":"/svg/QQ.svg","link":"tencent://AddContact/?fromId=45&fromSubId=1&subcmd=all&uin=2822688858"}}}},"mapped":true,"prev_post":{"title":"无穷级数的性质","uid":"8c5051666bb20a88e04fe467e55f2664","slug":"无穷级数的性质","date":"2023-07-15T07:46:56.000Z","updated":"2023-07-15T08:50:56.156Z","comments":true,"path":"api/articles/无穷级数的性质.json","keywords":null,"cover":"https://cdn.jsdelivr.net/gh/GeneralK1ng/My_Blog_IMG@main/img/isolated-math-formulas-on-white-background-free-vector.jpg","text":"欢迎来到无穷级数的奇妙世界！在这一章中，我们将探索无穷级数的性质，包括收敛、发散以及我们可以对级数进行的代数运算。理解这些性质对于数学和科学的许多领域都是至关重要的，它使我们能够做出准确的预测，解决重要的问题，并发展新的计算方法。所以，让我们一起深入探索无穷级数的惊人性质吧。 几...","link":"","photos":[],"count_time":{"symbolsCount":"4.1k","symbolsTime":"4 mins."},"categories":[],"tags":[{"name":"笔记","slug":"笔记","count":47,"path":"api/tags/笔记.json"},{"name":"Math","slug":"Math","count":2,"path":"api/tags/Math.json"}],"author":{"name":"General_K1ng","slug":"blog-author","avatar":"https://cdn.jsdelivr.net/gh/GeneralK1ng/My_Blog_IMG@main/img/avatar.png","link":"/","description":"一名正在努力学习计算机的菜鸟","socials":{"github":"","twitter":"","stackoverflow":"","wechat":"","qq":"","weibo":"","zhihu":"","csdn":"","juejin":"","customs":{"bilibili":{"icon":"/svg/BILIBILI.svg","link":"https://space.bilibili.com/32927332"},"csdn":{"icon":"/svg/csdn.svg","link":"https://blog.csdn.net/qq_34849354"},"github":{"icon":"/svg/GitHub.svg","link":"https://github.com/GeneralK1ng"},"QQ":{"icon":"/svg/QQ.svg","link":"tencent://AddContact/?fromId=45&fromSubId=1&subcmd=all&uin=2822688858"}}}}},"next_post":{}}